acceptlang/__init__.py
acceptlang/py.typed
acceptlang-0.0.5.dist-info/LICENCE
acceptlang-0.0.5.dist-info/METADATA
acceptlang-0.0.5.dist-info/WHEEL
acceptlang-0.0.5.dist-info/top_level.txt
acceptlang-0.0.5.dist-info/RECORD
