Metadata-Version: 2.1
Name: acceptlang
Version: 0.0.5
Summary: A package for parsing Accept-Language tag received from (untrusted) client context.
Home-page: https://github.com/piotrszyma/acceptlang
Author: Piotr Szyma
Author-email: contact@piotrszyma.pl
Project-URL: Bug Reports, https://github.com/piotrszyma/acceptlang/issues
Project-URL: Source, https://github.com/piotrszyma/acceptlang
Classifier: Development Status :: 3 - Alpha
Requires-Python: >=3.7, <4
License-File: LICENCE
